MANIFEST.in
README.md
requirements.txt
setup.py
CatLearn.egg-info/PKG-INFO
CatLearn.egg-info/SOURCES.txt
CatLearn.egg-info/dependency_links.txt
CatLearn.egg-info/requires.txt
CatLearn.egg-info/top_level.txt
catlearn/__init__.py
catlearn/active_learning/__init__.py
catlearn/active_learning/acquisition_functions.py
catlearn/active_learning/algorithm.py
catlearn/api/__init__.py
catlearn/api/ase_atoms_api.py
catlearn/api/ase_data_setup.py
catlearn/api/catmap.py
catlearn/api/networkx_graph_api.py
catlearn/api/magpie/Magpie.jar
catlearn/api/magpie/exes/voroExt.exe
catlearn/api/magpie/exes/voroExt_MACOS.exe
catlearn/api/magpie/exes/voroExt_windows.exe
catlearn/api/magpie/lookup-data/Abbreviation.table
catlearn/api/magpie/lookup-data/AtomicVolume.table
catlearn/api/magpie/lookup-data/AtomicWeight.table
catlearn/api/magpie/lookup-data/BoilingT.table
catlearn/api/magpie/lookup-data/BoilingTemp.table
catlearn/api/magpie/lookup-data/BulkModulus.table
catlearn/api/magpie/lookup-data/Column.table
catlearn/api/magpie/lookup-data/CovalentRadius.table
catlearn/api/magpie/lookup-data/Density.table
catlearn/api/magpie/lookup-data/DipolePolarizability.table
catlearn/api/magpie/lookup-data/ElectronAffinity.table
catlearn/api/magpie/lookup-data/Electronegativity.table
catlearn/api/magpie/lookup-data/FirstIonizationEnergy.table
catlearn/api/magpie/lookup-data/FusionEnthalpy.table
catlearn/api/magpie/lookup-data/GSbandgap.table
catlearn/api/magpie/lookup-data/GSenergy_pa.table
catlearn/api/magpie/lookup-data/GSestBCClatcnt.table
catlearn/api/magpie/lookup-data/GSestFCClatcnt.table
catlearn/api/magpie/lookup-data/GSmagmom.table
catlearn/api/magpie/lookup-data/GSvolume_pa.table
catlearn/api/magpie/lookup-data/HHIp.table
catlearn/api/magpie/lookup-data/HHIr.table
catlearn/api/magpie/lookup-data/HeatCapacityMass.table
catlearn/api/magpie/lookup-data/HeatCapacityMolar.table
catlearn/api/magpie/lookup-data/HeatFusion.table
catlearn/api/magpie/lookup-data/ICSDVolume.table
catlearn/api/magpie/lookup-data/IonizationEnergies.table
catlearn/api/magpie/lookup-data/IsAlkali.table
catlearn/api/magpie/lookup-data/IsDBlock.table
