Metadata-Version: 2.1
Name: CatLearn
Version: 0.6.1
Summary: Machine Learning using atomic-scale calculations.
Home-page: https://github.com/SUNCAT-Center/CatLearn
Author: Paul C. Jennings
Author-email: pcjennings@stanford.edu
License: GPL-3.0
Platform: UNKNOWN
Classifier: Development Status :: 4 - Beta
Classifier: Programming Language :: Python
Classifier: Programming Language :: Python :: 2
Classifier: Programming Language :: Python :: 2.7
Classifier: Programming Language :: Python :: 3
Classifier: Programming Language :: Python :: 3.5
Classifier: Programming Language :: Python :: 3.6
Requires-Python: >=2.7, !=3.0.*, !=3.1.*, !=3.2.*, !=3.3.*, !=3.4.*, <4
